llm_structured_output/__init__.py
llm_structured_output/acceptor.py
llm_structured_output/json_acceptor.py
llm_structured_output/json_schema_acceptor.py
llm_structured_output/util/__init__.py
llm_structured_output/util/bitmap.py
llm_structured_output/util/output.py
llm_structured_output/util/tokenization.py
llm_structured_output/util/tokentrie.py
llm_structured_output-0.0.20.dist-info/METADATA
llm_structured_output-0.0.20.dist-info/WHEEL
llm_structured_output-0.0.20.dist-info/licenses/LICENSE
llm_structured_output-0.0.20.dist-info/RECORD
