Metadata-Version: 2.4
Name: llm_structured_output
Version: 0.0.20
Summary: Constrain LLM generation to structured output, such as function calling and tool use
Project-URL: Homepage, https://github.com/otriscon/llm-structured-output
Project-URL: Issues, https://github.com/otriscon/llm-structured-output/issues
Author-email: "Oscar D.P. Triscon" <github@triscon.com>
License-File: LICENSE
Classifier: License :: OSI Approved :: MIT License
Classifier: Operating System :: OS Independent
Classifier: Programming Language :: Python :: 3
Requires-Python: >=3.8
